ruststartracker/__init__.py
ruststartracker/catalog.py
ruststartracker/gaia_data_j2016.csv
ruststartracker/hipparcos_data_j1991.25.csv
ruststartracker/libruststartracker.pyi
ruststartracker/libruststartracker.so
ruststartracker/py.typed
ruststartracker/star.py
ruststartracker/test_backend.py
ruststartracker/test_catalog.py
ruststartracker/test_integration.py
ruststartracker/test_star.py
ruststartracker-0.2.9.dist-info/METADATA
ruststartracker-0.2.9.dist-info/WHEEL
ruststartracker-0.2.9.dist-info/licenses/LICENSE
ruststartracker-0.2.9.dist-info/RECORD
