Metadata-Version: 2.4
Name: ruststartracker
Version: 0.2.9
Summary: Lightweight Python Star Tracker With Rust Backend
License: MIT
License-File: LICENSE
Author: Nicolas Tobler
Author-email: nitobler@gmail.com
Requires-Python: >=3.10,<4.0
Classifier: License :: OSI Approved :: MIT License
Classifier: Programming Language :: Python :: 3
Classifier: Programming Language :: Python :: 3.10
Classifier: Programming Language :: Python :: 3.11
Classifier: Programming Language :: Python :: 3.12
Classifier: Programming Language :: Python :: 3.13
Classifier: Programming Language :: Python :: 3.14
Requires-Dist: numpy (>=1.26.0,<2.0.0)
Requires-Dist: opencv-python-headless (>=4.9.0,<5.0.0)
Project-URL: GaiaAttribution, https://www.cosmos.esa.int/gaia
Project-URL: Homepage, https://github.com/ntobler/ruststartracker
Project-URL: License, https://opensource.org/licenses/MIT
